AUTHORS.rst
CHANGES.rst
MANIFEST.in
README.rst
setup.py
humilis_push_processor/__init__.py
humilis_push_processor/meta.yaml.j2
humilis_push_processor/outputs.yaml.j2
humilis_push_processor/plugin.py
humilis_push_processor/resources.yaml.j2
humilis_push_processor.egg-info/PKG-INFO
humilis_push_processor.egg-info/SOURCES.txt
humilis_push_processor.egg-info/dependency_links.txt
humilis_push_processor.egg-info/entry_points.txt
humilis_push_processor.egg-info/not-zip-safe
humilis_push_processor.egg-info/requires.txt
humilis_push_processor.egg-info/top_level.txt
humilis_push_processor/lambda_function/__init__.py
humilis_push_processor/lambda_function/setup.py
humilis_push_processor/lambda_function/handler/__init__.py
humilis_push_processor/lambda_function/handler/processor.py