Metadata-Version: 1.1
Name: humilis-push-processor
Version: 0.0.10
Summary: Humilis push event processor plugin
Home-page: http://github.com/humilis/humilis-push-processor
Author: German Gomez-Herrero, FindHotel and others
Author-email: data@findhotel.net
License: MIT
Platform: UNKNOWN
Classifier: Programming Language :: Python :: 3
Classifier: Programming Language :: Python :: 2
